{
    "steps": [
        {
            "name": "gcr.io/cloud-builders/docker",
            "args": [
                "build",
                "-t",
                "testbuild",
                "."
            ]
        }
    ],
    "serviceAccount": "predict@iainvisa.iam.gserviceaccount.com",
    "images": [
        "europe-west1-docker.pkg.dev/iainvisa/images/predictimg/"
    ],
    "substitutions": {},
    "options": {
		"defaultLogsBucketBehavior": "REGIONAL_USER_OWNED_BUCKET"
	},
    "queueTtl": "3600s",
    "secrets": [],
    "timeout": "600s",
    "tags": [],
    "artifacts": {}
}
